bin/convert_hf_to_gguf.py
bin/llama-gemma3-cli
bin/llama-llava-cli
bin/llama-llava-clip-quantize-cli
bin/llama-minicpmv-cli
bin/llama-qwen2vl-cli
include/ggml-alloc.h
include/ggml-backend.h
include/ggml-blas.h
include/ggml-cann.h
include/ggml-cpp.h
include/ggml-cpu.h
include/ggml-cuda.h
include/ggml-kompute.h
include/ggml-metal.h
include/ggml-opt.h
include/ggml-rpc.h
include/ggml-sycl.h
include/ggml-vulkan.h
include/ggml.h
include/gguf.h
include/llama-cpp.h
include/llama.h
lib/cmake/ggml/ggml-config.cmake
lib/cmake/ggml/ggml-version.cmake
lib/cmake/llama/llama-config.cmake
lib/cmake/llama/llama-version.cmake
lib/libggml-base.dylib
lib/libggml-blas.dylib
lib/libggml-cpu.dylib
lib/libggml-metal.dylib
lib/libggml.dylib
lib/libllama.dylib
lib/libllava.dylib
lib/pkgconfig/llama.pc
llama_core/.DS_Store
llama_core/__init__.py
llama_core/__main__.py
llama_core/_ctypes_extensions.py
llama_core/_ggml.py
llama_core/_internals.py
llama_core/_logger.py
llama_core/_utils.py
llama_core/cli.py
llama_core/const.py
llama_core/container.py
llama_core/diskcache/__init__.py
llama_core/diskcache/cli.py
llama_core/diskcache/core.py
llama_core/diskcache/djangocache.py
llama_core/diskcache/fanout.py
llama_core/diskcache/persistent.py
llama_core/diskcache/recipes.py
llama_core/gui.py
llama_core/lib/libggml-base.dylib
llama_core/lib/libggml-blas.dylib
llama_core/lib/libggml-cpu.dylib
llama_core/lib/libggml-metal.dylib
llama_core/lib/libggml.dylib
llama_core/lib/libllama.dylib
llama_core/lib/libllava.dylib
llama_core/llama.py
llama_core/llama_cache.py
llama_core/llama_chat_format.py
llama_core/llama_cpp.py
llama_core/llama_grammar.py
llama_core/llama_speculative.py
llama_core/llama_tokenizer.py
llama_core/llama_types.py
llama_core/llava_cpp.py
llama_core/logo.png
llama_core/menu.py
llama_core/parse.py
llama_core/parser.py
llama_core/pdf/.DS_Store
llama_core/pdf/__init__.py
llama_core/pdf/_cmap.py
llama_core/pdf/_codecs/__init__.py
llama_core/pdf/_codecs/adobe_glyphs.py
llama_core-0.4.2.dist-info/METADATA
llama_core-0.4.2.dist-info/WHEEL
llama_core-0.4.2.dist-info/licenses/LICENSE.md
llama_core-0.4.2.dist-info/RECORD
