Metadata-Version: 2.1
Name: llama_core
Version: 0.4.2
Summary: gguf connector core built on llama.cpp
Author-Email: calcuis <info@calcu.io>
License: MIT
Classifier: Programming Language :: Python :: 3
Classifier: Programming Language :: Python :: 3.8
Classifier: Programming Language :: Python :: 3.9
Classifier: Programming Language :: Python :: 3.10
Classifier: Programming Language :: Python :: 3.11
Classifier: Programming Language :: Python :: 3.12
Classifier: Programming Language :: Python :: 3.13
Project-URL: Homepage, https://github.com/calcuis/llama-core
Project-URL: Issues, https://github.com/calcuis/llama-core/issues
Requires-Python: >=3.8
Requires-Dist: typing-extensions>=4.5.0
Requires-Dist: diskcache>=5.6.1
Requires-Dist: jinja2>=3.1.3
Requires-Dist: numpy>=1.26.4
Requires-Dist: pocketsphinx>=5.0.3
Requires-Dist: speechrecognition>=3.10.3
Provides-Extra: server
Requires-Dist: uvicorn>=0.22.0; extra == "server"
Requires-Dist: fastapi>=0.100.0; extra == "server"
Requires-Dist: pydantic-settings>=2.0.1; extra == "server"
Requires-Dist: sse-starlette>=1.6.1; extra == "server"
Requires-Dist: starlette-context<0.4,>=0.3.6; extra == "server"
Requires-Dist: PyYAML>=5.1; extra == "server"
Provides-Extra: test
Requires-Dist: pytest>=7.4.0; extra == "test"
Requires-Dist: httpx>=0.24.1; extra == "test"
Requires-Dist: scipy>=1.10; extra == "test"
Requires-Dist: fastapi>=0.100.0; extra == "test"
Requires-Dist: sse-starlette>=1.6.1; extra == "test"
Requires-Dist: starlette-context<0.4,>=0.3.6; extra == "test"
Requires-Dist: pydantic-settings>=2.0.1; extra == "test"
Requires-Dist: huggingface-hub>=0.23.0; extra == "test"
Provides-Extra: dev
Requires-Dist: black>=23.3.0; extra == "dev"
Requires-Dist: twine>=4.0.2; extra == "dev"
Requires-Dist: mkdocs>=1.4.3; extra == "dev"
Requires-Dist: mkdocstrings[python]>=0.22.0; extra == "dev"
Requires-Dist: mkdocs-material>=9.1.18; extra == "dev"
Requires-Dist: pytest>=7.4.0; extra == "dev"
Requires-Dist: httpx>=0.24.1; extra == "dev"
Provides-Extra: all
Requires-Dist: llama_core[dev,server,test]; extra == "all"
